insituTEM/__ init __.py
insituTEM/insitu_DP.py
insituTEM/insitu_IO.py
insituTEM/insitu_Preprocess.py
insituTEM/insitu_alignment.py
insituTEM-0.1.6.dist-info/METADATA
insituTEM-0.1.6.dist-info/WHEEL
insituTEM-0.1.6.dist-info/top_level.txt
insituTEM-0.1.6.dist-info/RECORD
