Metadata-Version: 2.1
Name: insituTEM
Version: 0.1.6
Summary: A package of tools for processing in situ TEM data
Author: Meng Li
Requires-Dist: tifffile
Requires-Dist: moviepy
Requires-Dist: tqdm
Requires-Dist: numpy
Requires-Dist: opencv-python
Requires-Dist: scipy
Requires-Dist: matplotlib
